setup.py
slackhook/__init__.py
slackhook/hook.py
slackhook.egg-info/PKG-INFO
slackhook.egg-info/SOURCES.txt
slackhook.egg-info/dependency_links.txt
slackhook.egg-info/requires.txt
slackhook.egg-info/top_level.txt