Metadata-Version: 1.1
Name: slackhook
Version: 0.1.3
Summary: Simple, Slack webhook integration for Flask application 
Home-page: https://github.com/MichaelYusko/slackhook
Author: Michael Yusko
Author-email: freshjelly12@yahoo.com
License: UNKNOWN
Platform: UNKNOWN
Classifier: Development Status :: 5 - Production/Stable
Classifier: Environment :: Web Environment
Classifier: Programming Language :: Python :: 2.7
Classifier: Programming Language :: Python :: 3.5
Classifier: Programming Language :: Python :: 3.6
Classifier: License :: OSI Approved :: MIT License
